backgroundr/__init__.py
backgroundr/background_creation.py
backgroundr/cli.py
backgroundr/font_paths.py
backgroundr/settings.py
backgroundr/fonts/__init__.py
backgroundr/fonts/font_paths.py
backgroundr/fonts/Open_Sans/OpenSans-Bold.ttf
backgroundr/fonts/Open_Sans/OpenSans-BoldItalic.ttf
backgroundr/fonts/Open_Sans/OpenSans-ExtraBold.ttf
backgroundr/fonts/Open_Sans/OpenSans-ExtraBoldItalic.ttf
backgroundr/fonts/Open_Sans/OpenSans-Italic.ttf
backgroundr/fonts/Open_Sans/OpenSans-Light.ttf
backgroundr/fonts/Open_Sans/OpenSans-LightItalic.ttf
backgroundr/fonts/Open_Sans/OpenSans-Regular.ttf
backgroundr/fonts/Open_Sans/OpenSans-Semibold.ttf
backgroundr/fonts/Open_Sans/OpenSans-SemiboldItalic.ttf
backgroundr/fonts/Roboto/Roboto-Black.ttf
backgroundr/fonts/Roboto/Roboto-BlackItalic.ttf
backgroundr/fonts/Roboto/Roboto-Bold.ttf
backgroundr/fonts/Roboto/Roboto-BoldItalic.ttf
backgroundr/fonts/Roboto/Roboto-Italic.ttf
backgroundr/fonts/Roboto/Roboto-Light.ttf
backgroundr/fonts/Roboto/Roboto-LightItalic.ttf
backgroundr/fonts/Roboto/Roboto-Medium.ttf
backgroundr/fonts/Roboto/Roboto-MediumItalic.ttf
backgroundr/fonts/Roboto/Roboto-Regular.ttf
backgroundr/fonts/Roboto/Roboto-Thin.ttf
backgroundr/fonts/Roboto/Roboto-ThinItalic.ttf
backgroundr/fonts/Slabo_27px/Slabo27px-Regular.ttf
Backgroundr-1.1.11.dist-info/DESCRIPTION.rst
Backgroundr-1.1.11.dist-info/METADATA
Backgroundr-1.1.11.dist-info/metadata.json
Backgroundr-1.1.11.dist-info/RECORD
Backgroundr-1.1.11.dist-info/top_level.txt
Backgroundr-1.1.11.dist-info/WHEEL
fonts/__init__.py
fonts/font_paths.py
