Metadata-Version: 2.0
Name: Backgroundr
Version: 1.1.11
Summary: A simple way to create backgrounds for your computer with custom colors and text
Home-page: https://github.com/smg247/backgroundr
Author: Stephen Goeddel
Author-email: stephen@stephengoeddel.com
License: UNKNOWN
Keywords: Backgrounds Wallpapers Images
Platform: UNKNOWN
Requires-Dist: Pillow
